{"title":"A winter survey on the Punatsangchhu: searching for the world's rarest heron","markdown":{"yaml":{"title":"A winter survey on the Punatsangchhu: searching for the world's rarest heron","description":"The Punatsangchhu is one of Bhutan's great rivers — fast, cold, and flanked by sal forest and gravel bars. For a few months each winter it hosts one of the last holdouts of the White-bellied Heron. This is what a survey day looks like.","author":"Indra P. Acharja","date":"2024-03-10","categories":["Field Notes","White-bellied Heron","Bhutan"],"image":""},"headingText":"Why the Punatsangchhu","containsRefs":false,"markdown":"\n\nThe alarm sounds at 4:30am. Outside, the Punatsangchhu valley is still dark, and the river — audible even from the guesthouse — is running fast and cold from the glaciers upstream. By the time we reach the survey point, the sky is turning from black to a deep, slate blue.\n\nThis is the time. If there is a White-bellied Heron on this stretch, it will be moving to its feeding sites before full daylight.\n\n\nThe Punatsangchhu river basin in central Bhutan is one of the most important known sites for the White-bellied Heron globally. It has consistently held the largest concentration of the species — at peak counts, between 10 and 15 individuals have been recorded here — and it contains several of the few known active breeding territories.\n\nWhat makes it suitable is a combination of factors: sections of fast-flowing, boulder-strewn river with gravel bars and clear water that hold the large fish the herons depend on; intact riverine forest along the banks for nesting; and relatively low human disturbance in key segments. The Punatsangchhu is not pristine — there is fishing pressure, some agricultural encroachment at the margins, and the shadow of a major hydropower project — but it remains the closest thing to optimal habitat this species has anywhere.\n\n## The survey protocol\n\nWe conduct point counts at fixed locations along the river, separated by a distance that prevents double-counting. Each survey point is watched for 20 minutes. We record all White-bellied Herons seen or heard, and note behaviour: flying, feeding, resting, or engaged in territory interactions.\n\nThe work is slow and often yields nothing. A single survey morning might produce zero detections across a stretch that we know holds herons. The birds are cryptic, they move long distances, and in winter some individuals shift to different parts of the river system. A zero count doesn't mean the heron isn't there.\n\nThis is one of the core challenges of monitoring an extremely rare species: the detection probability for any individual in any single survey is low. Building a reliable population estimate requires repeated surveys across multiple sites and seasons, analyzed with statistical models that explicitly account for imperfect detection.\n\n## What we have learned about numbers\n\nWhen I began systematic surveys of the Punatsangchhu in 2015, the population appeared stable — between 8 and 12 individuals detected annually in this basin. By the early 2020s, the picture had become more concerning. Detections were more variable between years, and — most worryingly — the number of successful nesting attempts appeared to be declining.\n\nOur 2025 paper in *Avian Conservation and Ecology* uses an integrated population model to synthesize these data and project forward under different conservation scenarios. The results are sobering. Without active intervention, the modelled probability of extinction within decades is not negligible.\n\n## A note on hope\n\nThis is heavy work to carry. Every winter, when I walk these riverbanks, I am aware that the birds I am looking for may number fewer than the fingers on two hands in this entire river system.\n\nBut there is also something remarkable about being here at all — that this species persists, that people in Bhutan have dedicated their careers to protecting it, that a growing international community of researchers and conservationists cares deeply about its future. The Punatsangchhu at dawn, with the chance that a White-bellied Heron might appear from the mist and alight on a gravel bar, is one of the most extraordinary experiences in birdwatching. That it is still possible is worth protecting.\n","srcMarkdownNoYaml":"\n\nThe alarm sounds at 4:30am. Outside, the Punatsangchhu valley is still dark, and the river — audible even from the guesthouse — is running fast and cold from the glaciers upstream. By the time we reach the survey point, the sky is turning from black to a deep, slate blue.\n\nThis is the time. If there is a White-bellied Heron on this stretch, it will be moving to its feeding sites before full daylight.\n\n## Why the Punatsangchhu\n\nThe Punatsangchhu river basin in central Bhutan is one of the most important known sites for the White-bellied Heron globally. It has consistently held the largest concentration of the species — at peak counts, between 10 and 15 individuals have been recorded here — and it contains several of the few known active breeding territories.\n\nWhat makes it suitable is a combination of factors: sections of fast-flowing, boulder-strewn river with gravel bars and clear water that hold the large fish the herons depend on; intact riverine forest along the banks for nesting; and relatively low human disturbance in key segments. The Punatsangchhu is not pristine — there is fishing pressure, some agricultural encroachment at the margins, and the shadow of a major hydropower project — but it remains the closest thing to optimal habitat this species has anywhere.\n\n## The survey protocol\n\nWe conduct point counts at fixed locations along the river, separated by a distance that prevents double-counting. Each survey point is watched for 20 minutes. We record all White-bellied Herons seen or heard, and note behaviour: flying, feeding, resting, or engaged in territory interactions.\n\nThe work is slow and often yields nothing. A single survey morning might produce zero detections across a stretch that we know holds herons. The birds are cryptic, they move long distances, and in winter some individuals shift to different parts of the river system. A zero count doesn't mean the heron isn't there.\n\nThis is one of the core challenges of monitoring an extremely rare species: the detection probability for any individual in any single survey is low. Building a reliable population estimate requires repeated surveys across multiple sites and seasons, analyzed with statistical models that explicitly account for imperfect detection.\n\n## What we have learned about numbers\n\nWhen I began systematic surveys of the Punatsangchhu in 2015, the population appeared stable — between 8 and 12 individuals detected annually in this basin. By the early 2020s, the picture had become more concerning. Detections were more variable between years, and — most worryingly — the number of successful nesting attempts appeared to be declining.\n\nOur 2025 paper in *Avian Conservation and Ecology* uses an integrated population model to synthesize these data and project forward under different conservation scenarios. The results are sobering. Without active intervention, the modelled probability of extinction within decades is not negligible.\n\n## A note on hope\n\nThis is heavy work to carry. Every winter, when I walk these riverbanks, I am aware that the birds I am looking for may number fewer than the fingers on two hands in this entire river system.\n\nBut there is also something remarkable about being here at all — that this species persists, that people in Bhutan have dedicated their careers to protecting it, that a growing international community of researchers and conservationists cares deeply about its future. The Punatsangchhu at dawn, with the chance that a White-bellied Heron might appear from the mist and alight on a gravel bar, is one of the most extraordinary experiences in birdwatching. That it is still possible is worth protecting.\n"},"formats":{"html":{"identifier":{"display-name":"HTML","target-format":"html","base-format":"html"},"execute":{"fig-width":7,"fig-height":5,"fig-format":"retina","fig-dpi":96,"df-print":"default","error":false,"eval":true,"cache":null,"freeze":"auto","echo":true,"output":true,"warning":true,"include":true,"keep-md":false,"keep-ipynb":false,"ipynb":null,"enabled":null,"daemon":null,"daemon-restart":false,"debug":false,"ipynb-filters":[],"ipynb-shell-interactivity":null,"plotly-connected":true,"engine":"markdown"},"render":{"keep-tex":false,"keep-typ":false,"keep-source":false,"keep-hidden":false,"prefer-html":false,"output-divs":true,"output-ext":"html","fig-align":"default","fig-pos":null,"fig-env":null,"code-fold":"none","code-overflow":"scroll","code-link":false,"code-line-numbers":false,"code-tools":false,"tbl-colwidths":"auto","merge-includes":true,"inline-includes":false,"preserve-yaml":false,"latex-auto-mk":true,"latex-auto-install":true,"latex-clean":true,"latex-min-runs":1,"latex-max-runs":10,"latex-makeindex":"makeindex","latex-makeindex-opts":[],"latex-tlmgr-opts":[],"latex-input-paths":[],"latex-output-dir":null,"link-external-icon":false,"link-external-newwindow":true,"self-contained-math":false,"format-resources":[],"notebook-links":true},"pandoc":{"standalone":true,"wrap":"none","default-image-extension":"png","to":"html","toc":false,"html-math-method":"katex","include-after-body":["../_post-social.html"],"output-file":"index.html"},"language":{"toc-title-document":"Table of contents","toc-title-website":"On this page","related-formats-title":"Other Formats","related-notebooks-title":"Notebooks","source-notebooks-prefix":"Source","other-links-title":"Other Links","code-links-title":"Code Links","launch-dev-container-title":"Launch Dev Container","launch-binder-title":"Launch Binder","article-notebook-label":"Article Notebook","notebook-preview-download":"Download Notebook","notebook-preview-download-src":"Download Source","notebook-preview-back":"Back to Article","manuscript-meca-bundle":"MECA Bundle","section-title-abstract":"Abstract","section-title-appendices":"Appendices","section-title-footnotes":"Footnotes","section-title-references":"References","section-title-reuse":"Reuse","section-title-copyright":"Copyright","section-title-citation":"Citation","appendix-attribution-cite-as":"For attribution, please cite this work as:","appendix-attribution-bibtex":"BibTeX citation:","appendix-view-license":"View License","title-block-author-single":"Author","title-block-author-plural":"Authors","title-block-affiliation-single":"Affiliation","title-block-affiliation-plural":"Affiliations","title-block-published":"Published","title-block-modified":"Modified","title-block-keywords":"Keywords","callout-tip-title":"Tip","callout-note-title":"Note","callout-warning-title":"Warning","callout-important-title":"Important","callout-caution-title":"Caution","code-summary":"Code","code-tools-menu-caption":"Code","code-tools-show-all-code":"Show All Code","code-tools-hide-all-code":"Hide All Code","code-tools-view-source":"View Source","code-tools-source-code":"Source Code","tools-share":"Share","tools-download":"Download","code-line":"Line","code-lines":"Lines","copy-button-tooltip":"Copy to Clipboard","copy-button-tooltip-success":"Copied!","repo-action-links-edit":"Edit this page","repo-action-links-source":"View source","repo-action-links-issue":"Report an issue","back-to-top":"Back to top","search-no-results-text":"No results","search-matching-documents-text":"matching documents","search-copy-link-title":"Copy link to search","search-hide-matches-text":"Hide additional matches","search-more-match-text":"more match in this document","search-more-matches-text":"more matches in this document","search-clear-button-title":"Clear","search-text-placeholder":"","search-detached-cancel-button-title":"Cancel","search-submit-button-title":"Submit","search-label":"Search","toggle-section":"Toggle section","toggle-sidebar":"Toggle sidebar navigation","toggle-dark-mode":"Toggle dark mode","toggle-reader-mode":"Toggle reader mode","toggle-navigation":"Toggle navigation","crossref-fig-title":"Figure","crossref-tbl-title":"Table","crossref-lst-title":"Listing","crossref-thm-title":"Theorem","crossref-lem-title":"Lemma","crossref-cor-title":"Corollary","crossref-prp-title":"Proposition","crossref-cnj-title":"Conjecture","crossref-def-title":"Definition","crossref-exm-title":"Example","crossref-exr-title":"Exercise","crossref-ch-prefix":"Chapter","crossref-apx-prefix":"Appendix","crossref-sec-prefix":"Section","crossref-eq-prefix":"Equation","crossref-lof-title":"List of Figures","crossref-lot-title":"List of Tables","crossref-lol-title":"List of Listings","environment-proof-title":"Proof","environment-remark-title":"Remark","environment-solution-title":"Solution","listing-page-order-by":"Order By","listing-page-order-by-default":"Default","listing-page-order-by-date-asc":"Oldest","listing-page-order-by-date-desc":"Newest","listing-page-order-by-number-desc":"High to Low","listing-page-order-by-number-asc":"Low to High","listing-page-field-date":"Date","listing-page-field-title":"Title","listing-page-field-description":"Description","listing-page-field-author":"Author","listing-page-field-filename":"File Name","listing-page-field-filemodified":"Modified","listing-page-field-subtitle":"Subtitle","listing-page-field-readingtime":"Reading Time","listing-page-field-wordcount":"Word Count","listing-page-field-categories":"Categories","listing-page-minutes-compact":"{0} min","listing-page-category-all":"All","listing-page-no-matches":"No matching items","listing-page-words":"{0} words","listing-page-filter":"Filter","draft":"Draft"},"metadata":{"lang":"en","fig-responsive":true,"quarto-version":"1.9.37","engines":[{"path":"C:\\Program Files\\Quarto\\share\\extension-subtrees\\julia-engine\\_extensions\\julia-engine\\julia-engine.js"}],"theme":["cosmo","../../styles.css"],"title":"A winter survey on the Punatsangchhu: searching for the world's rarest heron","description":"The Punatsangchhu is one of Bhutan's great rivers — fast, cold, and flanked by sal forest and gravel bars. For a few months each winter it hosts one of the last holdouts of the White-bellied Heron. This is what a survey day looks like.","author":"Indra P. Acharja","date":"2024-03-10","categories":["Field Notes","White-bellied Heron","Bhutan"],"image":""},"extensions":{"book":{"multiFile":true}}}},"projectFormats":["html"]}